{
  "hash": "fd5ff992",
  "configHash": "1f5fbe45",
  "lockfileHash": "e89b65ea",
  "browserHash": "c4a6ec0a",
  "optimized": {
    "react": {
      "src": "../../node_modules/react/index.js",
      "file": "react.js",
      "fileHash": "25f4f948",
      "needsInterop": true
    },
    "react-dom/client": {
      "src": "../../node_modules/react-dom/client.js",
      "file": "react-dom_client.js",
      "fileHash": "6e9f1915",
      "needsInterop": true
    },
    "react-router-dom": {
      "src": "../../node_modules/react-router-dom/dist/index.js",
      "file": "react-router-dom.js",
      "fileHash": "829a25a2",
      "needsInterop": false
    },
    "react-dom": {
      "src": "../../node_modules/react-dom/index.js",
      "file": "react-dom.js",
      "fileHash": "7e59ebb2",
      "needsInterop": true
    }
  },
  "chunks": {
    "chunk-GT3PTVOL": {
      "file": "chunk-GT3PTVOL.js"
    },
    "chunk-UTEJFLXC": {
      "file": "chunk-UTEJFLXC.js"
    }
  }
}